{
  "conceptId": "777ffdd6e240",
  "canonical_zh": "戏剧体戏剧",
  "reviewedAt": "2026-05-05T13:10:59.881Z",
  "verdict": "pass",
  "score": 9,
  "issues": [
    {
      "section": "origins",
      "type": "hallucination",
      "severity": "medium",
      "description": "条目称布莱希特「认为亚里士多德的辩证法是单线的，其戏剧观强调「相似」而忽视「不相似」的同等必要性」——证据原文确实提到「亚里士多德不是不懂辩证法的思想家，但是他的辩证法是单线的」，并以「鸟飞到绘制的葡萄上」为例说明「相似是必要的，但不相似也是必要的」。但条目将这段论述定性为布莱希特对「亚里士多德式戏剧学」（即戏剧体戏剧）的批评，而证据中这段话是在讨论「非亚里士多德式戏剧学」的背景下出现，语境是辩证法与典型概念，并非直接批评戏剧体戏剧形式本身。归因方向基本正确但存在语境简化。",
      "suggestion": "可改为：布莱希特在论证非亚里士多德戏剧学时，指出亚里士多德的辩证法是单线的，仅强调「相似」而忽视「不相似」的同等必要性，以此为史诗体戏剧的认识论基础背书。"
    },
    {
      "section": "examples",
      "type": "hallucination",
      "severity": "low",
      "description": "条目称「以「波鲁斯为儿子痛苦」为例，质疑观众被强制感受角色痛苦的合理性」——证据原文中W说「以波鲁斯为例。也许他儿子是个坏蛋。尽管如此，他会感到痛苦，可我为什么要这样呢？」这是对话中W（非布莱希特）的发言，条目将其归为「布莱希特」的论证略有失准，但整体意思相符，严重性低。",
      "suggestion": "可改为「对话中以「波鲁斯为儿子痛苦」为例，探讨观众是否应被强制沉浸在角色痛苦中的问题」，不直接归因为布莱希特本人的论断。"
    }
  ],
  "corrections": {},
  "costUsd": 0
}