{
  "conceptId": "b20225998520",
  "canonical_zh": "情节模式",
  "reviewedAt": "2026-05-05T19:29:15.679Z",
  "verdict": "pass",
  "score": 9,
  "issues": [
    {
      "section": "examples",
      "type": "hallucination",
      "severity": "medium",
      "description": "条目称《虎豹小霸王》主角为「布屈与圣得西」，原文为「布屈·卡西迪和圣得西」，省略了「卡西迪」姓氏，属于不完整引用，但不构成幻觉。然而条目称「追逐直至故事末尾」表述准确。更值得注意的是：条目未提及原文列举的《寻找宝石》《黑色星期五》《月光光心慌慌》《猛鬼街》《猎杀红色十月》等案例，属于选择性省略，可接受。",
      "suggestion": "此条目的例子选取有代表性，省略次要案例合理，无需修改。"
    },
    {
      "section": "origins",
      "type": "missing",
      "severity": "low",
      "description": "原文中提到「答案一：谁知道？成千上万，甚至没准数百万呢」作为第一种主张，且说明这是「课堂上和写作教材中常常听到的答案」。条目的origins部分仅列了69种、36种、两种三个主张，未提及「无数种」这一常见答案，略有遗漏，但对核心论点影响不大。",
      "suggestion": "可在origins中补充「也有人认为情节数量无穷无尽」作为第一种主张，以还原原文四种答案的完整性。"
    }
  ],
  "corrections": {},
  "costUsd": 0
}