{
  "conceptId": "b4a8c4bb5afa",
  "canonical_zh": "来龙去脉",
  "reviewedAt": "2026-05-05T23:49:05.210Z",
  "verdict": "pass",
  "score": 9,
  "issues": [
    {
      "section": "examples",
      "type": "missing",
      "severity": "low",
      "description": "证据中明确提到结局是「罗尼·布莱克里受了重伤，也许会伤重至死」，条目将其表述为「枪击事件」但未提及受伤者姓名；另外证据说是「巴巴拉·哈利斯拿起麦克风带领大家歌唱」，条目仅说「人群在恐惧中再度高唱」，省略了具体人物，尚属合理简化，但可补充。",
      "suggestion": "可在examples中补充「罗尼·布莱克里中枪受伤，巴巴拉·哈利斯拿起麦克风带领人群高唱」，使细节更贴近原文。"
    },
    {
      "section": "applications",
      "type": "missing",
      "severity": "low",
      "description": "证据提到编剧特沃克斯伯里（Teweksbury）曾「两次到纳施维尔去进行调查研究，每一次都呆上几个星期」，条目写作「两度深入当地调研数周」，表述基本准确；但证据原文强调她「认识到影片中的主人公就是纳施维尔这座城市本身」是调研的重要成果，条目未体现这一因果关系。",
      "suggestion": "可补充：正是通过调研，编剧才发现城市本身即主人公这一核心认知，从而确立了全片的来龙去脉框架。"
    }
  ],
  "corrections": {},
  "costUsd": 0
}